Spades/__init__.py
Spades/admin.py
Spades/api.py
Spades/models.py
Spades/serializers.py
Spades/tests.py
Spades/urls.py
Spades/migrations/0001_initial.py
Spades/migrations/0002_event_user.py
Spades/migrations/0003_auto_20210329_0809.py
Spades/migrations/0004_alter_event_id_alter_event_info.py
Spades/migrations/__init__.py
Spades/static/Spades/css/eventadmin.css
Spades/static/Spades/js/eventadmin.js
Spades/static/Spades/js/prettyjson.js
django_spades-0.1.10.dist-info/LICENSE
django_spades-0.1.10.dist-info/METADATA
django_spades-0.1.10.dist-info/WHEEL
django_spades-0.1.10.dist-info/top_level.txt
django_spades-0.1.10.dist-info/RECORD
